{
  "원천엔젤스": {
    "예배비": {
      "원천엔젤스": {
        "사례인건비": {
          "지휘자": ["지휘자 사례비"],
          "보조교사": ["보조교사 사례비"],
          "반주자": ["반주자 사례비"]
        },
        "비품구입비": {
          "악보대": []
        },
        "행사비": {
          "연주행사": []
        },
        "운영비": {
          "간식비": ["악기 및 소모품"]
        }
      }
    }
  },
  "교육부": {
    "교육비": {
      "주일학교": {
        "교재비": {
          "교재": ["교재 구입비"]
        },
        "강사비": {
          "강사A": ["강사A 사례비"],
          "강사B": ["강사B 사례비"]
        }
      },
      "청년부": {
        "운영비": {
          "행사": ["행사 진행비"]
        }
      }
    }
  }
}
